{
	"info": {
		"_postman_id": "9bae88b7-1e29-426c-8a48-4a6af146d14a",
		"name": "local",
		"schema": "https://schema.getpostman.com/json/collection/v2.1.0/collection.json"
	},
	"item": [
		{
			"name": "user",
			"item": [
				{
					"name": "login",
					"event": [
						{
							"listen": "prerequest",
							"script": {
								"exec": [
									""
								],
								"type": "text/javascript"
							}
						},
						{
							"listen": "test",
							"script": {
								"exec": [
									"//把json字符串转化为对象\r",
									"var data=JSON.parse(responseBody);\r",
									"\r",
									"var token=data.data.token;\r",
									"\r",
									"pm.globals.set(\"token\", token);\r",
									""
								],
								"type": "text/javascript"
							}
						}
					],
					"request": {
						"method": "POST",
						"header": [],
						"body": {
							"mode": "raw",
							"raw": "{\r\n    \"email\": \"wild@qq.com\",\r\n    \"password\":\"root\"\r\n}",
							"options": {
								"raw": {
									"language": "json"
								}
							}
						},
						"url": {
							"raw": "{{host}}/user/login",
							"host": [
								"{{host}}"
							],
							"path": [
								"user",
								"login"
							]
						}
					},
					"response": []
				}
			]
		},
		{
			"name": "demo get",
			"protocolProfileBehavior": {
				"disableBodyPruning": true
			},
			"request": {
				"method": "GET",
				"header": [
					{
						"key": "Content-Type",
						"name": "Content-Type",
						"value": "application/json",
						"type": "text"
					},
					{
						"key": "token",
						"value": "234",
						"type": "text"
					},
					{
						"key": "traceId",
						"value": "{{traceId}}",
						"type": "text"
					}
				],
				"body": {
					"mode": "raw",
					"raw": "{\"id\":23}",
					"options": {
						"raw": {
							"language": "json"
						}
					}
				},
				"url": {
					"raw": "{{host}}/demo/12",
					"host": [
						"{{host}}"
					],
					"path": [
						"demo",
						"12"
					]
				}
			},
			"response": []
		},
		{
			"name": "balance",
			"request": {
				"method": "GET",
				"header": [
					{
						"key": "traceId",
						"value": "{{traceId}}",
						"type": "text"
					},
					{
						"key": "",
						"value": "",
						"type": "text",
						"disabled": true
					}
				],
				"url": {
					"raw": "{{host}}/balance/get/wild",
					"host": [
						"{{host}}"
					],
					"path": [
						"balance",
						"get",
						"wild"
					],
					"query": [
						{
							"key": "traceId",
							"value": "{{traceId}}",
							"disabled": true
						}
					]
				}
			},
			"response": []
		},
		{
			"name": "balance  add",
			"request": {
				"method": "POST",
				"header": [],
				"body": {
					"mode": "raw",
					"raw": "{\r\n    \"userId\": \"wild\",\r\n    \"key\": \"3434\",\r\n    \"amount\": 1\r\n}",
					"options": {
						"raw": {
							"language": "json"
						}
					}
				},
				"url": {
					"raw": "http://localhost:8080/balance/add",
					"protocol": "http",
					"host": [
						"localhost"
					],
					"port": "8080",
					"path": [
						"balance",
						"add"
					]
				}
			},
			"response": []
		},
		{
			"name": "balance reduce",
			"event": [
				{
					"listen": "prerequest",
					"script": {
						"exec": [
							"pm.environment.set(\"random\",Math.round(new Date().getTime()));\r",
							"console.log(pm.environment.get(\"random\"));\r",
							"var moment = require(\"moment\");\r",
							"var data = moment().format(\" YYYY-MM-DD HH:mm:ss\");\r",
							"pm.environment.set(\"now\",data);\r",
							"console.log(pm.environment.get(\"now\"));"
						],
						"type": "text/javascript"
					}
				}
			],
			"request": {
				"method": "POST",
				"header": [
					{
						"key": "traceId",
						"value": "{{traceId}}",
						"type": "text"
					}
				],
				"body": {
					"mode": "raw",
					"raw": "{\r\n    \"userId\": \"wild\",\r\n    \"key\": \"{{random}}\",\r\n    \"amount\": 10,\r\n    \"tradeDateStr\":\"{{now}}\"\r\n}",
					"options": {
						"raw": {
							"language": "json"
						}
					}
				},
				"url": {
					"raw": "http://localhost:8080/achilles/balance/reduce",
					"protocol": "http",
					"host": [
						"localhost"
					],
					"port": "8080",
					"path": [
						"achilles",
						"balance",
						"reduce"
					]
				}
			},
			"response": []
		},
		{
			"name": "get name",
			"request": {
				"method": "GET",
				"header": [
					{
						"key": "traceId",
						"value": "{{traceId}}",
						"type": "text"
					}
				],
				"url": {
					"raw": "{{host}}/demo/get/34",
					"host": [
						"{{host}}"
					],
					"path": [
						"demo",
						"get",
						"34"
					]
				}
			},
			"response": []
		},
		{
			"name": "event",
			"event": [
				{
					"listen": "prerequest",
					"script": {
						"exec": [
							""
						],
						"type": "text/javascript"
					}
				}
			],
			"request": {
				"method": "GET",
				"header": [
					{
						"key": "traceId",
						"value": "{{traceId}}",
						"type": "text"
					}
				],
				"url": {
					"raw": "{{host}}/demo/event",
					"host": [
						"{{host}}"
					],
					"path": [
						"demo",
						"event"
					]
				}
			},
			"response": []
		},
		{
			"name": "{{host}}/demo/event",
			"event": [
				{
					"listen": "prerequest",
					"script": {
						"exec": [
							""
						],
						"type": "text/javascript"
					}
				}
			],
			"request": {
				"method": "GET",
				"header": [
					{
						"key": "traceId",
						"value": "{{traceId}}",
						"type": "text"
					},
					{
						"key": "token",
						"value": "{{token}}",
						"type": "text"
					}
				],
				"url": {
					"raw": "{{host}}/demo/event",
					"host": [
						"{{host}}"
					],
					"path": [
						"demo",
						"event"
					]
				}
			},
			"response": []
		}
	],
	"event": [
		{
			"listen": "prerequest",
			"script": {
				"type": "text/javascript",
				"exec": [
					"var moment = require(\"moment\");",
					"var data = moment().format(\"YYYYMMDDHHmmssSSS\");",
					"pm.environment.set(\"traceId\",data+\"_postman\");",
					"console.log(pm.environment.get(\"traceId\"));"
				]
			}
		},
		{
			"listen": "test",
			"script": {
				"type": "text/javascript",
				"exec": [
					""
				]
			}
		}
	]
}